yuppy/__init__.py
yuppy-0.0.0.dist-info/METADATA
yuppy-0.0.0.dist-info/WHEEL
yuppy-0.0.0.dist-info/top_level.txt
yuppy-0.0.0.dist-info/RECORD
