Metadata-Version: 2.1
Name: yuppy
Version: 0.0.0
Summary: Coming soon
